{"ongoing_trials": {}, "hyperparameters": {"space": [{"class_name": "Boolean", "config": {"name": "add_conv_layer", "default": true, "conditions": []}}, {"class_name": "Int", "config": {"name": "conv_filters", "default": 64, "conditions": [], "min_value": 64, "max_value": 128, "step": 64, "sampling": "linear"}}, {"class_name": "Int", "config": {"name": "dense_units", "default": 128, "conditions": [], "min_value": 128, "max_value": 256, "step": 128, "sampling": "linear"}}, {"class_name": "Float", "config": {"name": "learning_rate", "default": 0.001, "conditions": [], "min_value": 0.0001, "max_value": 0.001, "step": null, "sampling": "log"}}, {"class_name": "Choice", "config": {"name": "optimizer", "default": "adam", "conditions": [], "values": ["adam", "rmsprop", "sgd"], "ordered": false}}], "values": {"add_conv_layer": true, "conv_filters": 64, "dense_units": 128, "learning_rate": 0.001, "optimizer": "adam"}}, "start_order": ["00", "01", "02", "03", "04", "05", "06", "07", "08", "09"], "end_order": ["00", "01", "02", "03", "04", "05", "06", "07", "08", "09"], "run_times": {"00": 1, "01": 1, "02": 1, "03": 1, "04": 1, "05": 1, "06": 1, "07": 1, "08": 1, "09": 1}, "retry_queue": [], "seed": 2812, "seed_state": 2862, "tried_so_far": ["1b4f50a29c407d441087e8585d8fb8e3", "733792b2d777ee79e1fce2d87078aa97", "53a73ce87fafad29b8aa570e17efcdd1", "b93c327003460bfd0782816a7cc714d7", "4ef632b324509e53dc199b6c286a14ad", "95032c34944e94be4697381b3f188acf", "7a8f262e2868d9c799b8e21af185be28", "4cbfad897447d41aa9f2b06f4d09c17a", "205aacc2c98bb66e67153bcd76383234", "9e2496204f8889c8b22c99be839a76dd"], "id_to_hash": {"00": "733792b2d777ee79e1fce2d87078aa97", "01": "b93c327003460bfd0782816a7cc714d7", "02": "53a73ce87fafad29b8aa570e17efcdd1", "03": "4ef632b324509e53dc199b6c286a14ad", "04": "4cbfad897447d41aa9f2b06f4d09c17a", "05": "1b4f50a29c407d441087e8585d8fb8e3", "06": "9e2496204f8889c8b22c99be839a76dd", "07": "95032c34944e94be4697381b3f188acf", "08": "205aacc2c98bb66e67153bcd76383234", "09": "7a8f262e2868d9c799b8e21af185be28"}, "display": {"search_start": "2025-07-31T13:58:08.543727", "trial_start": {"00": "2025-07-31T13:58:08.543727", "01": "2025-07-31T13:59:07.917117", "02": "2025-07-31T14:01:51.521339", "03": "2025-07-31T14:04:29.486550", "04": "2025-07-31T14:06:17.984200", "05": "2025-07-31T14:08:20.376474", "06": "2025-07-31T14:10:02.445325", "07": "2025-07-31T14:12:50.245813", "08": "2025-07-31T14:14:05.476382", "09": "2025-07-31T14:16:12.689011"}, "trial_number": {"00": 1, "01": 2, "02": 3, "03": 4, "04": 5, "05": 6, "06": 7, "07": 8, "08": 9, "09": 10}}}